{"title":"网站人机验证 ip","slug":"网站人机验证ip","date":"2020-07-02","updated":"2020-07-02","comments":true,"path":"api/posts/10.json","excerpt":"<ul><li> 主题 </li></ul>","cover":null,"covers":null,"content":"<ul><li> 主题 </li></ul><a id=\"more\"></a>","url":"/posts/10/","min2read":"1","word4post":2,"prev_post":null,"next_post":{"title":"ip 代理池搭建","url":"/posts/9/"},"toc":"","categories":[{"name":"Hexo","path":"api/categories/Hexo.json","url":"/categories/Hexo/"}],"tags":[{"name":"Mustom","path":"api/tags/Mustom.json","url":"/tags/Mustom/"}]}