{"title":"python 调库简单实现建模","slug":"python调库简单建模预测","date":"2020-06-30","updated":"2020-06-30","comments":true,"path":"api/posts/8.json","excerpt":"<ul><li>python 建模库 </li><li> 实现建立合适模型并预测</li></ul>","cover":null,"covers":null,"content":"<ul><li>python 建模库 </li><li> 实现建立合适模型并预测</li></ul><a id=\"more\"></a>","url":"/posts/8/","min2read":"1","word4post":15,"prev_post":{"title":"ip 代理池搭建","url":"/posts/9/"},"next_post":{"title":"python 调库简单实现可视化","url":"/posts/00009/"},"toc":"","categories":[{"name":"python","path":"api/categories/python.json","url":"/categories/python/"}],"tags":[{"name":"数据建模","path":"api/tags/数据建模.json","url":"/tags/数据建模/"}]}