{"name":"版本升级","postlist":[{"title":"在线升级服务器搭建","slug":"在线升级服务器搭建","date":"2023-04-08","updated":"2023-04-08","path":"api/posts/1000.json","excerpt":"<ul><li>top</li><li> 配置 </li><li> 需要文件 </li></ul>","cover":"/gallery/md_tu/1000/1.png","content":null,"min2read":"1","word4post":192,"url":"/posts/1000/","categories":[{"name":"服务器搭建","path":"api/categories/服务器搭建.json","url":"/categories/服务器搭建/"}],"tags":[{"name":"服务器","path":"api/tags/服务器.json","url":"/tags/服务器/"},{"name":"局域网环境","path":"api/tags/局域网环境.json","url":"/tags/局域网环境/"},{"name":"版本升级","path":"api/tags/版本升级.json","url":"/tags/版本升级/"}]}]}